andesite/__init__.py
andesite/combined_client.py
andesite/discord.py
andesite/http_client.py
andesite/pools.py
andesite/state.py
andesite/transform.py
andesite/web_socket_client.py
andesite/web_socket_client_events.py
andesite/models/__init__.py
andesite/models/debug.py
andesite/models/filters.py
andesite/models/player.py
andesite/models/receive_operations.py
andesite/models/send_operations.py
andesite/models/track.py
andesite.py-0.2.4.dist-info/LICENSE
andesite.py-0.2.4.dist-info/METADATA
andesite.py-0.2.4.dist-info/WHEEL
andesite.py-0.2.4.dist-info/top_level.txt
andesite.py-0.2.4.dist-info/RECORD
