Metadata-Version: 2.1
Name: andesite.py
Version: 0.2.4
Summary: Andesite client for Python
Home-page: https://github.com/gieseladev/andesite.py
Author: Giesela Inc.
Author-email: team@giesela.dev
License: UNKNOWN
Platform: UNKNOWN
Requires-Python: ~=3.7
Requires-Dist: aiobservable
Requires-Dist: aiohttp
Requires-Dist: lettercase
Requires-Dist: websockets
Requires-Dist: yarl
